llama_index/readers/huggingface_fs/__init__.py
llama_index/readers/huggingface_fs/base.py
llama_index_readers_huggingface_fs-0.4.1.dist-info/METADATA
llama_index_readers_huggingface_fs-0.4.1.dist-info/WHEEL
llama_index_readers_huggingface_fs-0.4.1.dist-info/licenses/LICENSE
llama_index_readers_huggingface_fs-0.4.1.dist-info/RECORD
