Metadata-Version: 2.4
Name: llama-index-readers-huggingface-fs
Version: 0.4.1
Summary: llama-index readers huggingface fs integration
Author-email: Your Name <you@example.com>
Maintainer: jerryjliu
License-Expression: MIT
License-File: LICENSE
Keywords: face,filesystem,fs,hugging,huggingface
Requires-Python: <4.0,>=3.9
Requires-Dist: huggingface-hub>=0.20.3
Requires-Dist: llama-index-core<0.15,>=0.13.0
Requires-Dist: pandas
